meshcore_sansio/__init__.py
meshcore_sansio-0.0.1.dist-info/METADATA
meshcore_sansio-0.0.1.dist-info/WHEEL
meshcore_sansio-0.0.1.dist-info/licenses/LICENCE
meshcore_sansio-0.0.1.dist-info/RECORD
