Metadata-Version: 2.4
Name: meshcore_sansio
Version: 0.0.1
Summary: MeshCore protocol implementation Sans I/O
Project-URL: Source Code, https://codeberg.org/skyguy/meshcore-sansio
Author-email: Kevin Steen <code@kevinsteen.net>
License-Expression: AGPL-3.0-or-later
License-File: LICENCE
Classifier: Development Status :: 2 - Pre-Alpha
Classifier: Intended Audience :: Developers
Classifier: Operating System :: OS Independent
Classifier: Programming Language :: Python :: 3 :: Only
Requires-Python: >=3.7
